functionize_notebook-0.0.13.dist-info/licenses/AUTHORS.md
functionize_notebook-0.0.13.dist-info/licenses/LICENSE.txt
notebook_wrapper/__init__.py
functionize_notebook-0.0.13.dist-info/METADATA
functionize_notebook-0.0.13.dist-info/WHEEL
functionize_notebook-0.0.13.dist-info/top_level.txt
functionize_notebook-0.0.13.dist-info/RECORD
