Metadata-Version: 2.4
Name: functionize-notebook
Version: 0.0.13
Summary: run notebook like a function
Home-page: https://github.com/BuiHoangTu/functionize-notebook/
Author: Bui Hoang Tu
Author-email: bhtu.work@gmail.com
License: MIT
Classifier: License :: OSI Approved :: MIT License
License-File: LICENSE.txt
License-File: AUTHORS.md
Requires-Dist: nbformat
Requires-Dist: nbconvert
Requires-Dist: ipykernel
Requires-Dist: dill
Dynamic: author
Dynamic: author-email
Dynamic: classifier
Dynamic: description
Dynamic: description-content-type
Dynamic: home-page
Dynamic: license
Dynamic: license-file
Dynamic: requires-dist
Dynamic: summary
